lendSaaS/__init__.py
lendSaaS/__version__.py
lendSaaS/client.py
lendSaaS/src/base_lend_saas.py
lendSaaS/src/funding.py
lendSaaS/src/leads.py
lendSaaS/src/transactions.py
lendSaaS/src/underwriting.py
lend_saas-1.1.4.dist-info/LICENSE
lend_saas-1.1.4.dist-info/METADATA
lend_saas-1.1.4.dist-info/WHEEL
lend_saas-1.1.4.dist-info/top_level.txt
lend_saas-1.1.4.dist-info/RECORD
