Metadata-Version: 2.1
Name: lend-saas
Version: 1.1.4
Summary: A Python client library for LendSaaS.com
Home-page: https://github.com/uricod/lend-saas
Author: Josh Nussbaum
Author-email: joshnuss2@gmail.com
License: BSD
Platform: UNKNOWN
Classifier: Programming Language :: Python :: 3
Classifier: Programming Language :: Python :: 3.6
Classifier: Programming Language :: Python :: 3.7
Classifier: Programming Language :: Python :: 3.8
Classifier: Operating System :: OS Independent
Requires-Python: >=3.6
Requires-Dist: requests (==2.27.1)
Requires-Dist: pandas (==1.4.0)
